mach_cctt/__init__.py
mach_cctt/__main__.py
mach_cctt/config.py
mach_cctt/log.py
mach_cctt/utility.py
mach_cctt/withdraw.py
mach_cctt/aave/__init__.py
mach_cctt/aave/aave.py
mach_cctt/aave/event.py
mach_cctt/aave/rebalance_manager.py
mach_cctt/mach/__init__.py
mach_cctt/mach/destination_policy.py
mach_cctt/mach/event.py
abi/aave/pool.json
abi/aave/pool_addresses_provider.json
abi/aave/protocol_data_provider.json
mach_cctt-0.1.39.dist-info/METADATA
mach_cctt-0.1.39.dist-info/WHEEL
mach_cctt-0.1.39.dist-info/entry_points.txt
mach_cctt-0.1.39.dist-info/RECORD
