Metadata-Version: 2.4
Name: mach_cctt
Version: 0.1.39
Summary: Test automated trades on the Mach exchange.
Project-URL: Homepage, https://github.com/tristeroresearch/cross-chain-trade-test
Project-URL: Issues, https://github.com/tristeroresearch/cross-chain-trade-test/issues
Author-email: Richard Dong <richard@tristero.xyz>, Marwan Hassanien <marwan@stanford.edu>
Keywords: crypto,cryptocurrencies,cryptocurrency,defi,exchange,liquidity,mach,pool,swap,tristero
Classifier: Intended Audience :: Financial and Insurance Industry
Classifier: License :: Other/Proprietary License
Classifier: Operating System :: OS Independent
Classifier: Programming Language :: Python :: 3
Classifier: Topic :: Software Development :: Testing
Requires-Python: >=3.13.0
Requires-Dist: cachebox
Requires-Dist: eth-typing
Requires-Dist: mach-client>=0.1.77
Requires-Dist: pydantic
Requires-Dist: uvloop
Requires-Dist: web3
